whisper_key/__init__.py
whisper_key/audio_feedback.py
whisper_key/audio_recorder.py
whisper_key/clipboard_manager.py
whisper_key/config.defaults.yaml
whisper_key/config_manager.py
whisper_key/console_manager.py
whisper_key/hotkey_listener.py
whisper_key/instance_manager.py
whisper_key/main.py
whisper_key/model_registry.py
whisper_key/state_manager.py
whisper_key/system_tray.py
whisper_key/utils.py
whisper_key/voice_activity_detection.py
whisper_key/whisper_engine.py
whisper_key/assets/portaudio.dll
whisper_key/assets/tray_idle.png
whisper_key/assets/tray_processing.png
whisper_key/assets/tray_recording.png
whisper_key/assets/version.txt
whisper_key/assets/sounds/record_cancel.wav
whisper_key/assets/sounds/record_start.wav
whisper_key/assets/sounds/record_stop.wav
whisper_key_local-0.5.3.dist-info/METADATA
whisper_key_local-0.5.3.dist-info/WHEEL
whisper_key_local-0.5.3.dist-info/entry_points.txt
whisper_key_local-0.5.3.dist-info/top_level.txt
whisper_key_local-0.5.3.dist-info/RECORD
