Metadata-Version: 2.4
Name: whisper-key-local
Version: 0.5.3
Summary: Local faster-whisper speech-to-text app with global hotkeys for Windows
Author-email: Pin Wang <pinwang@gmail.com>
Requires-Python: >=3.11
Requires-Dist: faster-whisper>=1.2.1
Requires-Dist: ctranslate2>=4.6.3
Requires-Dist: numpy>=1.24.0
Requires-Dist: soxr>=0.3.0
Requires-Dist: sounddevice>=0.4.6
Requires-Dist: global-hotkeys>=0.1.7; platform_system == "Windows"
Requires-Dist: pyperclip>=1.8.2
Requires-Dist: ruamel.yaml>=0.18.14
Requires-Dist: pywin32>=306; platform_system == "Windows"
Requires-Dist: pyautogui>=0.9.54; platform_system == "Windows"
Requires-Dist: pystray>=0.19.5
Requires-Dist: Pillow>=10.0.0
Requires-Dist: hf-xet>=1.1.5
